hibp_py/__init__.py
hibp_py/__main__.py
hibp_py/ad.py
hibp_py/api.py
hibp_py/args.py
hibp_py/db.py
hibp_py/mail.py
hibp_py/report.py
hibp_py/utils.py
hibp_py-1.2.7.dist-info/METADATA
hibp_py-1.2.7.dist-info/WHEEL
hibp_py-1.2.7.dist-info/licenses/LICENSE
hibp_py-1.2.7.dist-info/RECORD
