Metadata-Version: 2.3
Name: hibp-py
Version: 1.2.7
Summary: Python utility for Have I Been Pwned API
Project-URL: homepage, https://github.com/Pavel-Sushko/hibp-py
Project-URL: issues, https://github.com/Pavel-Sushko/hibp-py/issues
Author-email: Pavel Sushko <github@psushko.com>
Classifier: Development Status :: 4 - Beta
Classifier: Environment :: Console
Classifier: Intended Audience :: Developers
Classifier: License :: OSI Approved :: MIT License
Classifier: Operating System :: MacOS :: MacOS X
Classifier: Operating System :: Microsoft :: Windows
Classifier: Operating System :: POSIX :: Linux
Classifier: Programming Language :: Python :: 3
Classifier: Programming Language :: Python :: 3 :: Only
Classifier: Programming Language :: Python :: 3.11
Classifier: Programming Language :: Python :: 3.12
Requires-Python: >=3.11
Requires-Dist: python-dotenv
Requires-Dist: requests
